[
  {"model": "kickhub.sizes", "pk": 1, "fields": {"item": 1, "size": "8", "quantity": 10}},
  {"model": "kickhub.sizes", "pk": 2, "fields": {"item": 1, "size": "9", "quantity": 8}},
  {"model": "kickhub.sizes", "pk": 3, "fields": {"item": 1, "size": "10", "quantity": 5}},
  {"model": "kickhub.sizes", "pk": 4, "fields": {"item": 2, "size": "7", "quantity": 12}},
  {"model": "kickhub.sizes", "pk": 5, "fields": {"item": 2, "size": "8", "quantity": 7}},
  {"model": "kickhub.sizes", "pk": 6, "fields": {"item": 3, "size": "9", "quantity": 15}},
  {"model": "kickhub.sizes", "pk": 7, "fields": {"item": 3, "size": "10", "quantity": 10}},
  {"model": "kickhub.sizes", "pk": 8, "fields": {"item": 4, "size": "8.5", "quantity": 6}},
  {"model": "kickhub.sizes", "pk": 9, "fields": {"item": 5, "size": "9", "quantity": 9}},
  {"model": "kickhub.sizes", "pk": 10, "fields": {"item": 6, "size": "11", "quantity": 4}},
  {"model": "kickhub.sizes", "pk": 11, "fields": {"item": 7, "size": "10", "quantity": 8}},
  {"model": "kickhub.sizes", "pk": 12, "fields": {"item": 8, "size": "9.5", "quantity": 5}},
  {"model": "kickhub.sizes", "pk": 13, "fields": {"item": 9, "size": "8", "quantity": 7}},
  {"model": "kickhub.sizes", "pk": 14, "fields": {"item": 10, "size": "10.5", "quantity": 3}},
  {"model": "kickhub.sizes", "pk": 15, "fields": {"item": 2, "size": "9", "quantity": 14}},
  {"model": "kickhub.sizes", "pk": 16, "fields": {"item": 3, "size": "8", "quantity": 11}},
  {"model": "kickhub.sizes", "pk": 17, "fields": {"item": 4, "size": "9", "quantity": 8}},
  {"model": "kickhub.sizes", "pk": 18, "fields": {"item": 5, "size": "10", "quantity": 6}},
  {"model": "kickhub.sizes", "pk": 19, "fields": {"item": 6, "size": "12", "quantity": 5}},
  {"model": "kickhub.sizes", "pk": 20, "fields": {"item": 7, "size": "11", "quantity": 7}},
  {"model": "kickhub.sizes", "pk": 21, "fields": {"item": 8, "size": "8", "quantity": 9}},
  {"model": "kickhub.sizes", "pk": 22, "fields": {"item": 9, "size": "10", "quantity": 4}},
  {"model": "kickhub.sizes", "pk": 23, "fields": {"item": 10, "size": "9", "quantity": 12}},
  {"model": "kickhub.sizes", "pk": 24, "fields": {"item": 1, "size": "11", "quantity": 7}},
  {"model": "kickhub.sizes", "pk": 25, "fields": {"item": 2, "size": "10", "quantity": 9}},
  {"model": "kickhub.sizes", "pk": 26, "fields": {"item": 3, "size": "11", "quantity": 8}},
  {"model": "kickhub.sizes", "pk": 27, "fields": {"item": 4, "size": "10", "quantity": 6}},
  {"model": "kickhub.sizes", "pk": 28, "fields": {"item": 5, "size": "8", "quantity": 10}},
  {"model": "kickhub.sizes", "pk": 29, "fields": {"item": 6, "size": "10.5", "quantity": 5}},
  {"model": "kickhub.sizes", "pk": 30, "fields": {"item": 7, "size": "9.5", "quantity": 7}},
  {"model": "kickhub.sizes", "pk": 31, "fields": {"item": 8, "size": "10", "quantity": 8}},
  {"model": "kickhub.sizes", "pk": 32, "fields": {"item": 9, "size": "11", "quantity": 6}},
  {"model": "kickhub.sizes", "pk": 33, "fields": {"item": 10, "size": "12", "quantity": 4}},
  {"model": "kickhub.sizes", "pk": 34, "fields": {"item": 1, "size": "12", "quantity": 3}},
  {"model": "kickhub.sizes", "pk": 35, "fields": {"item": 2, "size": "11.5", "quantity": 2}},
  {"model": "kickhub.sizes", "pk": 36, "fields": {"item": 3, "size": "12", "quantity": 5}},
  {"model": "kickhub.sizes", "pk": 37, "fields": {"item": 4, "size": "11", "quantity": 7}},
  {"model": "kickhub.sizes", "pk": 38, "fields": {"item": 5, "size": "9.5", "quantity": 6}},
  {"model": "kickhub.sizes", "pk": 39, "fields": {"item": 6, "size": "8.5", "quantity": 8}},
  {"model": "kickhub.sizes", "pk": 40, "fields": {"item": 7, "size": "8", "quantity": 9}},
  {"model": "kickhub.sizes", "pk": 41, "fields": {"item": 8, "size": "11.5", "quantity": 4}},
  {"model": "kickhub.sizes", "pk": 42, "fields": {"item": 9, "size": "8.5", "quantity": 5}},
  {"model": "kickhub.sizes", "pk": 43, "fields": {"item": 10, "size": "8", "quantity": 7}}
]
